strataregula/__init__.py
strataregula/kernel.py
strataregula/py.typed
strataregula/cli/__init__.py
strataregula/cli/compile_command.py
strataregula/cli/index_cli.py
strataregula/cli/main.py
strataregula/core/__init__.py
strataregula/core/compatibility.py
strataregula/core/compiler.py
strataregula/core/config_compiler.py
strataregula/core/pattern_expander.py
strataregula/golden/__init__.py
strataregula/golden/adaptive.py
strataregula/golden/history.py
strataregula/golden/optimized.py
strataregula/hierarchy/__init__.py
strataregula/hierarchy/commands.py
strataregula/hierarchy/merger.py
strataregula/hierarchy/processor.py
strataregula/index/__init__.py
strataregula/index/base.py
strataregula/index/content_search.py
strataregula/index/loader.py
strataregula/index/providers/fastindex.py
strataregula/json_processor/__init__.py
strataregula/json_processor/commands.py
strataregula/json_processor/converter.py
strataregula/json_processor/jsonpath.py
strataregula/json_processor/validator.py
strataregula/legacy/__init__.py
strataregula/passes/__init__.py
strataregula/passes/intern.py
strataregula/plugins/__init__.py
strataregula/plugins/config.py
strataregula/plugins/error_handling.py
strataregula/plugins/loader.py
strataregula/plugins/manager.py
strataregula/plugins/samples.py
strataregula/protocols/websocket.py
strataregula/stream/__init__.py
strataregula/stream/chunker.py
strataregula/stream/processor.py
strataregula-0.3.0.dist-info/licenses/LICENSE
strataregula-0.3.0.dist-info/METADATA
strataregula-0.3.0.dist-info/WHEEL
strataregula-0.3.0.dist-info/entry_points.txt
strataregula-0.3.0.dist-info/top_level.txt
strataregula-0.3.0.dist-info/RECORD
