Metadata-Version: 2.4
Name: strataregula
Version: 0.3.0
Summary: Layered Configuration Management with Strata Rules Architecture
Author-email: Strataregula Team <team@strataregula.com>
Maintainer-email: Strataregula Team <team@strataregula.com>
License: Apache-2.0
Project-URL: Homepage, https://github.com/strataregula/strataregula
Project-URL: Documentation, https://strataregula.readthedocs.io/
Project-URL: Repository, https://github.com/strataregula/strataregula
Project-URL: Bug Tracker, https://github.com/strataregula/strataregula/issues
Project-URL: Discussions, https://github.com/strataregula/strataregula/discussions
Project-URL: Changelog, https://github.com/strataregula/strataregula/blob/main/CHANGELOG.md
Project-URL: Performance Benchmarks, https://strataregula.github.io/strataregula/benchmark.html
Keywords: yaml,configuration,pattern,compiler,expansion,infrastructure,automation,cli,streaming,pipe,strata,layered,hierarchical,rules,engine
Classifier: Development Status :: 4 - Beta
Classifier: Intended Audience :: Developers
Classifier: Intended Audience :: System Administrators
Classifier: License :: OSI Approved :: Apache Software License
Classifier: Operating System :: OS Independent
Classifier: Programming Language :: Python :: 3
Classifier: Programming Language :: Python :: 3.8
Classifier: Programming Language :: Python :: 3.9
Classifier: Programming Language :: Python :: 3.10
Classifier: Programming Language :: Python :: 3.11
Classifier: Programming Language :: Python :: 3.12
Classifier: Topic :: Software Development :: Code Generators
Classifier: Topic :: System :: Systems Administration
Classifier: Topic :: Utilities
Classifier: Topic :: Software Development :: Libraries :: Python Modules
Classifier: Topic :: Text Processing :: Markup
Classifier: Typing :: Typed
Requires-Python: ==3.11.*
License-File: LICENSE
Requires-Dist: click>=7.0.0
Requires-Dist: rich>=10.0.0
Requires-Dist: pyyaml>=5.4.0
Requires-Dist: typing-extensions>=3.10.0
Requires-Dist: tomli>=1.2.0; python_version < "3.11"
Provides-Extra: dev
Requires-Dist: pytest>=7.0.0; extra == "dev"
Requires-Dist: pytest-cov>=4.0.0; extra == "dev"
Requires-Dist: mypy>=1.0.0; extra == "dev"
Requires-Dist: ruff>=0.1.0; extra == "dev"
Requires-Dist: bandit>=1.7.0; extra == "dev"
Requires-Dist: pre-commit>=3.0.0; extra == "dev"
Requires-Dist: build>=0.10.0; extra == "dev"
Requires-Dist: twine>=4.0.0; extra == "dev"
Provides-Extra: test
Requires-Dist: pytest>=7.0.0; extra == "test"
Requires-Dist: pytest-cov>=4.0.0; extra == "test"
Requires-Dist: pytest-mock>=3.10.0; extra == "test"
Requires-Dist: pytest-asyncio>=0.21.0; extra == "test"
Requires-Dist: pytest-benchmark>=4.0.0; extra == "test"
Provides-Extra: docs
Requires-Dist: mkdocs>=1.5.0; extra == "docs"
Requires-Dist: mkdocs-material>=9.0.0; extra == "docs"
Requires-Dist: mkdocstrings[python]>=0.24.0; extra == "docs"
Provides-Extra: performance
Requires-Dist: psutil>=5.7.0; extra == "performance"
Requires-Dist: matplotlib>=3.7.0; extra == "performance"
Requires-Dist: seaborn>=0.12.0; extra == "performance"
Requires-Dist: pandas>=2.0.0; extra == "performance"
Requires-Dist: jupyter>=1.0.0; extra == "performance"
Requires-Dist: nbconvert>=7.0.0; extra == "performance"
Provides-Extra: plugins
Requires-Dist: defusedxml>=0.7.1; extra == "plugins"
Provides-Extra: api
Requires-Dist: requests>=2.28.0; extra == "api"
Requires-Dist: httpx>=0.24.0; extra == "api"
Dynamic: license-file
